property_price_register/__init__.py
property_price_register/constants.py
property_price_register/utils.py
property_price_register/bin/__init__.py
property_price_register/bin/graph.py
property_price_register/bin/load.py
property_price_register/bin/merge_latest.py
property_price_register/bin/save.py
property_price_register/models/__init__.py
property_price_register/models/sale.py
property_price_register/resources/PPR.csv.tar.gz
property_price_register-0.0.24.dist-info/LICENSE
property_price_register-0.0.24.dist-info/METADATA
property_price_register-0.0.24.dist-info/WHEEL
property_price_register-0.0.24.dist-info/entry_points.txt
property_price_register-0.0.24.dist-info/top_level.txt
property_price_register-0.0.24.dist-info/RECORD
