Metadata-Version: 2.1
Name: property-price-register
Version: 0.0.24
Summary: UNKNOWN
Home-page: https://github.com/RobertLucey/property-price-register
Author: Robert Lucey
License: UNKNOWN
Platform: UNKNOWN
Requires-Python: >=3.9
License-File: LICENSE
Requires-Dist: cached-property
Requires-Dist: requests
Requires-Dist: pandas (>=1.3)
Requires-Dist: eircode (>=0.0.43)
Requires-Dist: bs4
Requires-Dist: matplotlib
